aiolifx_themes/__init__.py
aiolifx_themes/canvas.py
aiolifx_themes/generators/__init__.py
aiolifx_themes/generators/matrix.py
aiolifx_themes/generators/multizone.py
aiolifx_themes/generators/single.py
aiolifx_themes/library.py
aiolifx_themes/painter.py
aiolifx_themes/py.typed
aiolifx_themes/theme.py
aiolifx_themes/themes.py
aiolifx_themes/util.py
aiolifx_themes-1.0.3.dist-info/METADATA
aiolifx_themes-1.0.3.dist-info/WHEEL
aiolifx_themes-1.0.3.dist-info/licenses/LICENSE
aiolifx_themes-1.0.3.dist-info/RECORD
